cherryterm/__init__.py
cherryterm/cli.py
cherryterm-0.1.2.dist-info/LICENSE
cherryterm-0.1.2.dist-info/METADATA
cherryterm-0.1.2.dist-info/WHEEL
cherryterm-0.1.2.dist-info/entry_points.txt
cherryterm-0.1.2.dist-info/top_level.txt
cherryterm-0.1.2.dist-info/RECORD
