Metadata-Version: 2.1
Name: cherryterm
Version: 0.1.2
License-File: LICENSE
Requires-Dist: click
